{
  "frog_date": "2021-10-20",
  "frog_version": "1.0",
  "frog_curators": [],
  "frog_software": {
    "name": "fbc_curation",
    "version": "0.1.6",
    "url": "https://doi.org/10.5281/zenodo.3708271"
  },
  "software": {
    "name": "cameo",
    "version": "0.13.5",
    "url": "https://github.com/opencobra/cobrapy"
  },
  "solver": {
    "name": "glpk",
    "version": "5.0",
    "url": null
  },
  "model_filename": "e_coli_core.xml",
  "model_md5": "4574760460afe9e1b3388dc15f354706",
  "environment": "posix, Linux, 5.11.0-37-generic"
}